predi/__init__.py
predi/comparator.py
predi/config.py
predi/diversify_predicates.py
predi/parser.py
predi/simplifier.py
predi/tokenizer.py
predi-0.1.14.dist-info/LICENSE
predi-0.1.14.dist-info/METADATA
predi-0.1.14.dist-info/WHEEL
predi-0.1.14.dist-info/top_level.txt
predi-0.1.14.dist-info/RECORD
