Metadata-Version: 2.1
Name: predi
Version: 0.1.14
Summary: PreDi: Symbolic Solidity Predicate Difference Tool
Home-page: https://github.com/mojtaba-eshghie/PreDi
Author: Mojtaba Eshghie
Author-email: eshghie@kth.se
License: UNKNOWN
Platform: UNKNOWN
Classifier: Programming Language :: Python :: 3
Classifier: License :: OSI Approved :: MIT License
Classifier: Operating System :: OS Independent
Requires-Python: >=3.8
Requires-Dist: sympy >=1.13.0rc2
Requires-Dist: colorama >=0.4.6
Requires-Dist: pyyaml >=6.0.1
